mendec/__init__.py
mendec/__main__.py
mendec/_dec.py
mendec/_enc.py
mendec/key.py
mendec/keyfile.py
mendec/message.py
mendec/parallel.py
mendec/prime.py
mendec/test_enc_dec.py
mendec/utils.py
mendec/varint.py
mendec/cli/__init__.py
mendec/cli/decrypt.py
mendec/cli/encrypt.py
mendec/cli/keygen.py
mendec/cli/pick.py
mendec/cli/script.py
mendec/cli/test_cli.py
mendec-0.0.6.dist-info/LICENSE
mendec-0.0.6.dist-info/METADATA
mendec-0.0.6.dist-info/WHEEL
mendec-0.0.6.dist-info/entry_points.txt
mendec-0.0.6.dist-info/top_level.txt
mendec-0.0.6.dist-info/RECORD
