Metadata-Version: 2.1
Name: mendec
Version: 0.0.6
Summary: Message encrytion using RSA algorithm
Home-page: https://github.com/biojet1/mendec
Author: biojet1
Author-email: biojet1@gmail.com
Classifier: Intended Audience :: Developers
Classifier: Natural Language :: English
Classifier: License :: OSI Approved :: MIT License
Classifier: Operating System :: OS Independent
Classifier: Programming Language :: Python :: 3
Requires-Python: >=3.6
License-File: LICENSE
Requires-Dist: ocli
